odoo8_addon_web_menu_navbar_needaction-8.0.1.0.0.99.dev10-py2.7-nspkg.pth
odoo8_addon_web_menu_navbar_needaction-8.0.1.0.0.99.dev10.dist-info/METADATA
odoo8_addon_web_menu_navbar_needaction-8.0.1.0.0.99.dev10.dist-info/RECORD
odoo8_addon_web_menu_navbar_needaction-8.0.1.0.0.99.dev10.dist-info/WHEEL
odoo8_addon_web_menu_navbar_needaction-8.0.1.0.0.99.dev10.dist-info/namespace_packages.txt
odoo8_addon_web_menu_navbar_needaction-8.0.1.0.0.99.dev10.dist-info/top_level.txt
odoo_addons/web_menu_navbar_needaction/README.rst
odoo_addons/web_menu_navbar_needaction/__init__.py
odoo_addons/web_menu_navbar_needaction/__openerp__.py
odoo_addons/web_menu_navbar_needaction/data/ir_config_parameter.xml
odoo_addons/web_menu_navbar_needaction/i18n/es.po
odoo_addons/web_menu_navbar_needaction/i18n/fi.po
odoo_addons/web_menu_navbar_needaction/i18n/sl.po
odoo_addons/web_menu_navbar_needaction/i18n/web_menu_navbar_needaction.pot
odoo_addons/web_menu_navbar_needaction/models/__init__.py
odoo_addons/web_menu_navbar_needaction/models/ir_ui_menu.py
odoo_addons/web_menu_navbar_needaction/static/description/icon.png
odoo_addons/web_menu_navbar_needaction/static/src/css/web_menu_navbar_needaction.css
odoo_addons/web_menu_navbar_needaction/static/src/js/web_menu_navbar_needaction.js
odoo_addons/web_menu_navbar_needaction/tests/__init__.py
odoo_addons/web_menu_navbar_needaction/tests/test_web_menu_navbar_needaction.py
odoo_addons/web_menu_navbar_needaction/views/ir_ui_menu.xml
odoo_addons/web_menu_navbar_needaction/views/templates.xml
